Tushar_Package_STT/__init__.py
tushar_package_stt-1.1.3.dist-info/METADATA
tushar_package_stt-1.1.3.dist-info/WHEEL
tushar_package_stt-1.1.3.dist-info/top_level.txt
tushar_package_stt-1.1.3.dist-info/RECORD
