Metadata-Version: 2.4
Name: Tushar_Package_STT
Version: 1.1.3
Summary: A package for Speech-to-Text conversion using Selenium and a web-based STT helper, created by Tushar Varshney.
Author: Tushar Varshney
Author-email: tusharvarshney620@gmail.com
Dynamic: author
Dynamic: author-email
Dynamic: summary
